universal_robot_mcp/__init__.py
universal_robot_mcp/server.py
universal_robot_mcp-0.1.4.dist-info/METADATA
universal_robot_mcp-0.1.4.dist-info/WHEEL
universal_robot_mcp-0.1.4.dist-info/entry_points.txt
universal_robot_mcp-0.1.4.dist-info/top_level.txt
universal_robot_mcp-0.1.4.dist-info/RECORD
