Metadata-Version: 2.4
Name: universal-robot-mcp
Version: 0.1.4
Summary: MCP server for Universal Robots control
Author: roversx
License: GPL-3.0
Keywords: mcp,model-context-protocol,robot,urx,universal-robots
Classifier: Development Status :: 3 - Alpha
Classifier: Programming Language :: Python :: 3
Classifier: Programming Language :: Python :: 3.8
Classifier: Programming Language :: Python :: 3.9
Classifier: Programming Language :: Python :: 3.10
Classifier: Programming Language :: Python :: 3.11
Classifier: License :: OSI Approved :: GNU General Public License v3 (GPLv3)
Classifier: Operating System :: OS Independent
Classifier: Intended Audience :: Developers
Classifier: Topic :: Scientific/Engineering
Classifier: Topic :: Scientific/Engineering :: Artificial Intelligence
Requires-Python: >=3.8
Requires-Dist: mcp>=1.13.1
Requires-Dist: urx>=0.11.0
Requires-Dist: math3d==3.4.1
